[
  {
    "brand": "maybelline",
    "type": "lipstick",
    "series": "宝蓓爱炫彩护唇膏",
    "series_url": "https://www.maybellinechina.com/lip/lipbalm/babe-lip-loves-color",
    "name": "babe lip loves color",
    "color": "#f3a3bc"
  },
  {
    "brand": "maybelline",
    "type": "lipstick",
    "series": "宝蓓爱炫彩护唇膏",
    "series_url": "https://www.maybellinechina.com/lip/lipbalm/babe-lip-loves-color",
    "name": "恋粉",
    "color": "#ed7092"
  },
  {
    "brand": "maybelline",
    "type": "lipstick",
    "series": "宝蓓爱炫彩护唇膏",
    "series_url": "https://www.maybellinechina.com/lip/lipbalm/babe-lip-loves-color",
    "name": "紫吻",
    "color": "#e54792"
  },
  {
    "brand": "maybelline",
    "type": "lipstick",
    "series": "宝蓓爱炫彩护唇膏",
    "series_url": "https://www.maybellinechina.com/lip/lipbalm/babe-lip-loves-color",
    "name": "橘子",
    "color": "#f5a08b"
  },
  {
    "brand": "maybelline",
    "type": "lipstick",
    "series": "宝蓓爱炫彩护唇膏",
    "series_url": "https://www.maybellinechina.com/lip/lipbalm/babe-lip-loves-color",
    "name": "珊瑚",
    "color": "#f1846d"
  },
  {
    "brand": "maybelline",
    "type": "lipstick",
    "series": "宝蓓爱炫彩护唇膏",
    "series_url": "https://www.maybellinechina.com/lip/lipbalm/babe-lip-loves-color",
    "name": "樱粉",
    "color": "#f08686"
  },
  {
    "brand": "maybelline",
    "type": "lipstick",
    "series": "宝蓓爱炫彩护唇膏",
    "series_url": "https://www.maybellinechina.com/lip/lipbalm/babe-lip-loves-color",
    "name": "芭比",
    "color": "#e30e51"
  },
  {
    "brand": "maybelline",
    "type": "lipstick",
    "series": "宝蓓爱炫彩护唇膏",
    "series_url": "https://www.maybellinechina.com/lip/lipbalm/babe-lip-loves-color",
    "name": "蜜糖",
    "color": "#e0887e"
  }
]
